{"symbol": "PROK", "price": 1.93, "marketCap": 558762844, "beta": 1.864, "lastDividend": 0, "range": "0.54-7.13", "change": 0.03, "changePercentage": 1.57895, "volume": 386364, "averageVolume": 833854, "companyName": "ProKidney Corp.", "currency": "USD", "cik": "0001850270", "isin": "US74291D1046", "cusip": "74291D104", "exchangeFullName": "NASDAQ Capital Market", "exchange": "NASDAQ", "industry": "Biotechnology", "website": "https://www.prokidney.com", "description": "ProKidney Corp., a clinical-stage biotechnology, engages in developing cellular therapy candidates. It is developing Renal Autologous Cell Therapy, an autologous homologous cell admixture that is in a Phase III development program, as well as Phase II clinical trials for the treatment of moderate to severe diabetic kidney disease; and Phase I clinical trial for patients with congenital anomalies of the kidney and urinary tract. The company was founded in 2015 and is headquartered in Winston-Salem, North Carolina.", "ceo": "Bruce Culleton", "sector": "Healthcare", "country": "US", "fullTimeEmployees": "204", "phone": "336 999 7028", "address": "2000 Frontis Plaza Blvd.", "city": "Winston-Salem", "state": "NC", "zip": "27103", "image": "https://images.financialmodelingprep.com/symbol/PROK.png", "ipoDate": "2021-06-30", "defaultImage": false, "isEtf": false, "isActivelyTrading": true, "isAdr": false, "isFund": false}